{
	"response": [
		{
			"maintainer": "IczYn",
			"oem": "Google",
			"device": "Google Pixel 6 Pro",
			"filename": "AlphaDroid-14.0-20240824-raven-vanilla-v2.4.zip",
			"download": "https://sourceforge.net/projects/alphadroid-project/files/raven/AlphaDroid-14.0-20240824-raven-vanilla-v2.4.zip/download",
			"timestamp": 1724479663,
			"md5": "e715bf016048d2954fe5ebee9e54f3ab",
			"sha256": "25df85e646d28ddd9a23fe80c4055346b081f52ecd40bd0ef5fb9fa23f49108d",
			"size": 1644532867,
			"version": "2.4",
			"buildtype": "vanilla",
			"forum": "https://t.me/alphadroid_chat",
			"gapps": "",
			"firmware": "",
			"modem": "",
			"bootloader": "",
			"recovery": "https://drive.google.com/drive/folders/16w5bbm3-spnzBsI9Ul0vZGdHOmQaUrOP",
			"paypal": "https://www.paypal.me/iczyn",
			"telegram": "https://t.me/iczynbuilds",
			"dt": "https://github.com/AlphaDroid-devices/device_google_raviole",
			"common-dt": "",
			"kernel": "https://android.googlesource.com/device/google/raviole-kernel"
		}
	]
}
